bbdraw/__init__.py
bbdraw/bbdraw.py
bbdraw/color.py
bbdraw/polygon.py
bbdraw/text.py
bbdraw-0.1.dist-info/LICENSE
bbdraw-0.1.dist-info/METADATA
bbdraw-0.1.dist-info/WHEEL
bbdraw-0.1.dist-info/top_level.txt
bbdraw-0.1.dist-info/RECORD
