Metadata-Version: 2.1
Name: bbdraw
Version: 0.1
Summary: Library for drawing labeled bounding boxes / bounding polygons
Home-page: https://github.com/krasch/bbdraw
Author: krasch
Author-email: dev@krasch.io
License: MIT
Platform: UNKNOWN
Classifier: Development Status :: 3 - Alpha
Classifier: Intended Audience :: Developers
Classifier: Topic :: Software Development
Classifier: License :: OSI Approved :: MIT License
Classifier: Programming Language :: Python :: 3
Requires-Python: >=3.5
Requires-Dist: pillow (>=4.0)
